scratchsession/__init__.py
scratchsession/prepare_session.py
scratchsession-1.0.0.dist-info/LICENSE
scratchsession-1.0.0.dist-info/METADATA
scratchsession-1.0.0.dist-info/WHEEL
scratchsession-1.0.0.dist-info/top_level.txt
scratchsession-1.0.0.dist-info/RECORD
