Metadata-Version: 2.1
Name: scratchsession
Version: 1.0.0
Summary: A simple function for setting up scratch HTTP sessions.
Home-page: https://github.com/yuwex/scratchsession
Author: yuwex
License: UNKNOWN
Platform: UNKNOWN
Classifier: Development Status :: 5 - Production/Stable
Classifier: License :: OSI Approved :: MIT License
Classifier: Intended Audience :: Education
Classifier: Natural Language :: English
Classifier: Operating System :: OS Independent
Classifier: Programming Language :: Python :: 3.10
Classifier: Topic :: Software Development :: Libraries
Requires-Python: >=3.7
License-File: LICENSE
Requires-Dist: requests (>=2.2.0)
